orbdemod/__init__.py
orbdemod/costas.py
orbdemod/cr.py
orbdemod/ddc.py
orbdemod/decode.py
orbdemod/fletcher_ecc_save.py
orbdemod/logging_config.py
orbdemod/packet_utils.py
orbdemod/pipeline.py
orbdemod/plotting.py
orbdemod/rrc.py
orbdemod/timing_recovery.py
orbdemod-0.1.0.dist-info/licenses/LICENSE
orbdemod-0.1.0.dist-info/METADATA
orbdemod-0.1.0.dist-info/WHEEL
orbdemod-0.1.0.dist-info/top_level.txt
orbdemod-0.1.0.dist-info/RECORD
