Metadata-Version: 2.4
Name: orbdemod
Version: 0.1.0
Summary: ORBCOMM satellites downlink signal demodulator
Author-email: Yanbin Yang <yangyanbin@shao.ac.cn>
License: MIT License
Project-URL: Homepage, https://github.com/JinYi1108/Orbcomm_Demodulator
Project-URL: Data, https://zenodo.org/records/18213739
Project-URL: Software-DOI, https://doi.org/10.5281/zenodo.18214211
Classifier: Programming Language :: Python :: 3
Classifier: License :: OSI Approved :: MIT License
Classifier: Operating System :: OS Independent
Classifier: Topic :: Scientific/Engineering :: Astronomy
Requires-Python: >=3.8
License-File: LICENSE
Requires-Dist: numpy
Requires-Dist: matplotlib
Requires-Dist: scipy
Dynamic: license-file
